{"1000": {"Customer Name": "Shiv Prakash", "Address": "Samastipur", "Product ID": "202101", "Product Name": "Laptop", "Billing Amount": 86000},
 "1001": {"Customer Name": "Shiv Prakash", "Address": "Samastipur", "Product ID": "202102", "Product Name": "Mobile", "Billing Amount": 24000},
 "1002": {"Customer Name": "Swetant", "Address": "Patna", "Product ID": "202104", "Product Name": "Choclates", "Billing Amount": 400},
 "1003": {"Customer Name": "Swetant", "Address": "Patna", "Product ID": "202103", "Product Name": "Charger", "Billing Amount": 250},
 "1004": {"Customer Name": "Mukesh", "Address": "Darbhanga", "Product ID": "202106", "Product Name": "Chair", "Billing Amount": 2500},
 "1005": {"Customer Name": "Mukesh", "Address": "Darbhanga", "Product ID": "202105", "Product Name": "Table", "Billing Amount": 800},
 "1006": {"Customer Name": "Mukesh", "Address": "Darbhanga", "Product ID": "202104", "Product Name": "Choclates", "Billing Amount": 1600},
 "1007": {"Customer Name": "Rajesh", "Address": "Kolkata", "Product ID": "202107", "Product Name": "CFL Bulb", "Billing Amount": 960},
 "1008": {"Customer Name": "Shruti Gupta", "Address": "Patna City", "Product ID": "202122", "Product Name": "Good Day", "Billing Amount": 210},
 "1009": {"Customer Name": "Shruti Gupta", "Address": "Patna City", "Product ID": "202116", "Product Name": "Dairy Milk", "Billing Amount": 480},
 "1010": {"Customer Name": "Madhu", "Address": "Muzaffarpur", "Product ID": "202115", "Product Name": "Thede Madhe", "Billing Amount": 50},
 "1011": {"Customer Name": "Madhu", "Address": "Muzaffarpur", "Product ID": "202130", "Product Name": "Sonpapdi", "Billing Amount": 420},
 "1012": {"Customer Name": "Madhu", "Address": "Muzaffarpur", "Product ID": "202118", "Product Name": "Kitkat", "Billing Amount": 100},
 "1013": {"Customer Name": "Avinal", "Address": "Purnia", "Product ID": "202120", "Product Name": "Munch", "Billing Amount": 50},
 "1014": {"Customer Name": "Avinal", "Address": "Purnia", "Product ID": "202111", "Product Name": "Sprite", "Billing Amount": 30},
 "1015": {"Customer Name": "Vimal", "Address": "Ara", "Product ID": "202123", "Product Name": "Top", "Billing Amount": 180},
 "1016": {"Customer Name": "Vimal", "Address": "Ara", "Product ID": "202116", "Product Name": "Dairy Milk", "Billing Amount": 400}}